earthworm/__init__.py
earthworm/hello.py
earthworm/hi.py
earthworm/pippip.py
earthworm_shubhamt619-0.0.5.dist-info/LICENSE
earthworm_shubhamt619-0.0.5.dist-info/METADATA
earthworm_shubhamt619-0.0.5.dist-info/WHEEL
earthworm_shubhamt619-0.0.5.dist-info/top_level.txt
earthworm_shubhamt619-0.0.5.dist-info/RECORD
