Metadata-Version: 2.1
Name: earthworm-shubhamt619
Version: 0.0.5
Summary: Boilerplate for Publishing Python Packages.
Home-page: https://github.com/shubhamt619/earthworm
Author: Shubham Thakur
Author-email: shubhamt619@gmail.com
License: UNKNOWN
Platform: UNKNOWN
Classifier: Programming Language :: Python :: 3
Classifier: License :: OSI Approved :: MIT License
Classifier: Operating System :: OS Independent
Classifier: Development Status :: 5 - Production/Stable
Classifier: Intended Audience :: Developers
Classifier: Natural Language :: English
Requires-Python: >=2.7
